<?xml version="1.0" encoding="utf-8" ?><dwsync><file name="zoomInLeft.css" server="readycodelive.com/public_html/christiancarabias.com/" local="3600852448" remote="3611599560" Dst="-1" /><file name="zoomIn.css" server="readycodelive.com/public_html/christiancarabias.com/" local="3600852448" remote="3611599560" Dst="-1" /><file name="zoomInRight.css" server="readycodelive.com/public_html/christiancarabias.com/" local="3600852448" remote="3611599560" Dst="-1" /><file name="zoomInDown.css" server="readycodelive.com/public_html/christiancarabias.com/" local="3600852448" remote="3611599560" Dst="-1" /><file name="zoomInUp.css" server="readycodelive.com/public_html/christiancarabias.com/" local="3600852448" remote="3611599560" Dst="-1" /><file name="zoomInLeft.css" server="www.readycodelive.com/public_html/artofavalentine/" local="3600852448" remote="3617575020" Dst="-1" /><file name="zoomIn.css" server="www.readycodelive.com/public_html/artofavalentine/" local="3600852448" remote="3617575020" Dst="-1" /><file name="zoomInRight.css" server="www.readycodelive.com/public_html/artofavalentine/" local="3600852448" remote="3617575020" Dst="-1" /><file name="zoomInDown.css" server="www.readycodelive.com/public_html/artofavalentine/" local="3600852448" remote="3617575020" Dst="-1" /><file name="zoomInUp.css" server="www.readycodelive.com/public_html/artofavalentine/" local="3600852448" remote="3617575020" Dst="-1" /><file name="zoomInLeft.css" server="artofavalentine.com" local="3600852448" remote="3617731020" Dst="-1" /><file name="zoomIn.css" server="artofavalentine.com" local="3600852448" remote="3617731020" Dst="-1" /><file name="zoomInRight.css" server="artofavalentine.com" local="3600852448" remote="3617731020" Dst="-1" /><file name="zoomInDown.css" server="artofavalentine.com" local="3600852448" remote="3617731020" Dst="-1" /><file name="zoomInUp.css" server="artofavalentine.com" local="3600852448" remote="3617731020" Dst="-1" /><file name="zoomInLeft.css" server="readycodelive.com/public_html/aaronarts/" local="3600852448" remote="3626029260" Dst="-1" /><file name="zoomIn.css" server="readycodelive.com/public_html/aaronarts/" local="3600852448" remote="3626029260" Dst="-1" /><file name="zoomInRight.css" server="readycodelive.com/public_html/aaronarts/" local="3600852448" remote="3626029260" Dst="-1" /><file name="zoomInDown.css" server="readycodelive.com/public_html/aaronarts/" local="3600852448" remote="3626029260" Dst="-1" /><file name="zoomInUp.css" server="readycodelive.com/public_html/aaronarts/" local="3600852448" remote="3626029260" Dst="-1" /><file name="zoomIn.css" server="aarondemar.com" local="3600852448" remote="3626260140" Dst="-1" /><file name="zoomInRight.css" server="aarondemar.com" local="3600852448" remote="3626260140" Dst="-1" /><file name="zoomInLeft.css" server="aarondemar.com" local="3600852448" remote="3626260140" Dst="-1" /><file name="zoomInDown.css" server="aarondemar.com" local="3600852448" remote="3626260140" Dst="-1" /><file name="zoomInUp.css" server="aarondemar.com" local="3600852448" remote="3626260140" Dst="-1" /><file name="zoomInLeft.css" server="us153.siteground.us" local="3732290676" remote="3732245580" Dst="-1" /><file name="zoomIn.css" server="us153.siteground.us" local="3732290676" remote="3732245580" Dst="-1" /><file name="zoomInRight.css" server="us153.siteground.us" local="3732290676" remote="3732245580" Dst="-1" /><file name="zoomInDown.css" server="us153.siteground.us" local="3732290676" remote="3732245580" Dst="-1" /><file name="zoomInUp.css" server="us153.siteground.us" local="3732290676" remote="3732245580" Dst="-1" /></dwsync>